adventofcode/__about__.py
adventofcode/__init__.py
adventofcode/cli.py
adventofcode/utils.py
adventofcode-25.12.dist-info/METADATA
adventofcode-25.12.dist-info/WHEEL
adventofcode-25.12.dist-info/entry_points.txt
adventofcode-25.12.dist-info/licenses/LICENSE
adventofcode-25.12.dist-info/RECORD
