Metadata-Version: 2.4
Name: adventofcode
Version: 25.12
Summary: Helper utilities for solving Advent of Code puzzles
Project-URL: Documentation, https://github.com/anze3db/adventofcode#readme
Project-URL: Issues, https://github.com/anze3db/adventofcode/issues
Project-URL: Source, https://github.com/anze3db/adventofcode
Project-URL: Mastodon, https://fosstodon.org/@anze3db
Project-URL: Twitter, https://twitter.com/anze3db
Author-email: Anže Pečar <anze@pecar.me>
License-Expression: MIT
License-File: LICENSE
Classifier: Development Status :: 4 - Beta
Classifier: Programming Language :: Python
Classifier: Programming Language :: Python :: 3.10
Classifier: Programming Language :: Python :: 3.11
Classifier: Programming Language :: Python :: 3.12
Classifier: Programming Language :: Python :: 3.13
Classifier: Programming Language :: Python :: 3.14
Classifier: Programming Language :: Python :: Implementation :: CPython
Classifier: Programming Language :: Python :: Implementation :: PyPy
Requires-Python: >=3.10
Requires-Dist: beautifulsoup4
Requires-Dist: percache
Requires-Dist: python-dotenv
Requires-Dist: requests
Requires-Dist: rich
